setup.py
mpython_conn/__init__.py
mpython_conn/mpython_conn.py
mpython_conn.egg-info/PKG-INFO
mpython_conn.egg-info/SOURCES.txt
mpython_conn.egg-info/dependency_links.txt
mpython_conn.egg-info/requires.txt
mpython_conn.egg-info/top_level.txt